enterprise_gateway/__init__.py
enterprise_gateway/__main__.py
enterprise_gateway/_version.py
enterprise_gateway/enterprisegatewayapp.py
enterprise_gateway/services/__init__.py
enterprise_gateway/services/kernels/__init__.py
enterprise_gateway/services/kernels/remotemanager.py
enterprise_gateway/services/kernelspecs/__init__.py
enterprise_gateway/services/kernelspecs/remotekernelspec.py
enterprise_gateway/services/processproxies/__init__.py
enterprise_gateway/services/processproxies/distributed.py
enterprise_gateway/services/processproxies/processproxy.py
enterprise_gateway/services/processproxies/yarn.py
enterprise_gateway/services/sessions/__init__.py
enterprise_gateway/services/sessions/kernelsessionmanager.py
jupyter_enterprise_gateway_kunliu-0.5.0.dev0.dist-info/DESCRIPTION.rst
jupyter_enterprise_gateway_kunliu-0.5.0.dev0.dist-info/METADATA
jupyter_enterprise_gateway_kunliu-0.5.0.dev0.dist-info/RECORD
jupyter_enterprise_gateway_kunliu-0.5.0.dev0.dist-info/WHEEL
jupyter_enterprise_gateway_kunliu-0.5.0.dev0.dist-info/entry_points.txt
jupyter_enterprise_gateway_kunliu-0.5.0.dev0.dist-info/metadata.json
jupyter_enterprise_gateway_kunliu-0.5.0.dev0.dist-info/top_level.txt
